datahub_dagster_plugin/__init__.py
datahub_dagster_plugin/datahub_dagster_plugin.py
datahub_dagster_plugin/client/__init__.py
datahub_dagster_plugin/client/dagster_generator.py
datahub_dagster_plugin/modules/__init__.py
datahub_dagster_plugin/modules/snowflake_pandas/__init__.py
datahub_dagster_plugin/modules/snowflake_pandas/datahub_snowflake_pandas_io_manager.py
datahub_dagster_plugin/modules/storage/__init__.py
datahub_dagster_plugin/modules/storage/datahub_db_io_manager.py
datahub_dagster_plugin/sensors/__init__.py
datahub_dagster_plugin/sensors/datahub_sensors.py
acryl_datahub_dagster_plugin-15.0.4.dist-info/METADATA
acryl_datahub_dagster_plugin-15.0.4.dist-info/WHEEL
acryl_datahub_dagster_plugin-15.0.4.dist-info/entry_points.txt
acryl_datahub_dagster_plugin-15.0.4.dist-info/top_level.txt
acryl_datahub_dagster_plugin-15.0.4.dist-info/RECORD
