Metadata-Version: 2.2
Name: acryl-datahub-dagster-plugin
Version: 15.0.4
Summary: Datahub Dagster plugin to capture executions and send to Datahub
Home-page: https://datahubproject.io/
License: Apache License 2.0
Project-URL: Documentation, https://datahubproject.io/docs/
Project-URL: Source, https://github.com/datahub-project/datahub
Project-URL: Changelog, https://github.com/datahub-project/datahub/releases
Classifier: Development Status :: 5 - Production/Stable
Classifier: Programming Language :: Python
Classifier: Programming Language :: Python :: 3
Classifier: Programming Language :: Python :: 3 :: Only
Classifier: Intended Audience :: Developers
Classifier: Intended Audience :: Information Technology
Classifier: Intended Audience :: System Administrators
Classifier: License :: OSI Approved
Classifier: License :: OSI Approved :: Apache Software License
Classifier: Operating System :: Unix
Classifier: Operating System :: POSIX :: Linux
Classifier: Environment :: Console
Classifier: Environment :: MacOS X
Classifier: Topic :: Software Development
Requires-Python: >=3.9
Requires-Dist: dagit>=1.3.3
Requires-Dist: acryl-datahub[datahub-rest,sql-parser]==15.0.4
Requires-Dist: dagster>=1.3.3
Provides-Extra: ignore
Provides-Extra: dev
Requires-Dist: types-click==0.1.12; extra == "dev"
Requires-Dist: dagster>=1.3.3; extra == "dev"
Requires-Dist: dagster-snowflake-pandas>=0.11.0; extra == "dev"
Requires-Dist: freezegun; extra == "dev"
Requires-Dist: types-toml; extra == "dev"
Requires-Dist: types-cachetools; extra == "dev"
Requires-Dist: ruff==0.9.2; extra == "dev"
Requires-Dist: sqlalchemy-stubs; extra == "dev"
Requires-Dist: types-setuptools; extra == "dev"
Requires-Dist: types-requests; extra == "dev"
Requires-Dist: dagit>=1.3.3; extra == "dev"
Requires-Dist: deepdiff!=8.0.0; extra == "dev"
Requires-Dist: pytest>=6.2.2; extra == "dev"
Requires-Dist: build; extra == "dev"
Requires-Dist: tox; extra == "dev"
Requires-Dist: coverage>=5.1; extra == "dev"
Requires-Dist: types-tabulate; extra == "dev"
Requires-Dist: pytest-cov>=2.8.1; extra == "dev"
Requires-Dist: pydantic!=1.10.3,>=1.10.0; extra == "dev"
Requires-Dist: types-dataclasses; extra == "dev"
Requires-Dist: types-six; extra == "dev"
Requires-Dist: types-freezegun; extra == "dev"
Requires-Dist: packaging; extra == "dev"
Requires-Dist: dagster-snowflake>=0.11.0; extra == "dev"
Requires-Dist: types-pytz; extra == "dev"
Requires-Dist: types-python-dateutil; extra == "dev"
Requires-Dist: requests-mock; extra == "dev"
Requires-Dist: types-PyYAML; extra == "dev"
Requires-Dist: jsonpickle; extra == "dev"
Requires-Dist: twine; extra == "dev"
Requires-Dist: dagster-aws>=0.11.0; extra == "dev"
Requires-Dist: acryl-datahub[datahub-rest,sql-parser]==15.0.4; extra == "dev"
Requires-Dist: mypy>=1.4.0; extra == "dev"
Requires-Dist: pytest-asyncio>=0.16.0; extra == "dev"
Provides-Extra: integration-tests
Requires-Dist: types-click==0.1.12; extra == "integration-tests"
Requires-Dist: dagster>=1.3.3; extra == "integration-tests"
Requires-Dist: dagster-snowflake-pandas>=0.11.0; extra == "integration-tests"
Requires-Dist: freezegun; extra == "integration-tests"
Requires-Dist: types-toml; extra == "integration-tests"
Requires-Dist: types-cachetools; extra == "integration-tests"
Requires-Dist: ruff==0.9.2; extra == "integration-tests"
Requires-Dist: sqlalchemy-stubs; extra == "integration-tests"
Requires-Dist: types-setuptools; extra == "integration-tests"
Requires-Dist: types-requests; extra == "integration-tests"
Requires-Dist: dagit>=1.3.3; extra == "integration-tests"
Requires-Dist: deepdiff!=8.0.0; extra == "integration-tests"
Requires-Dist: pytest>=6.2.2; extra == "integration-tests"
Requires-Dist: build; extra == "integration-tests"
Requires-Dist: tox; extra == "integration-tests"
Requires-Dist: coverage>=5.1; extra == "integration-tests"
Requires-Dist: types-tabulate; extra == "integration-tests"
Requires-Dist: pytest-cov>=2.8.1; extra == "integration-tests"
Requires-Dist: pydantic!=1.10.3,>=1.10.0; extra == "integration-tests"
Requires-Dist: types-dataclasses; extra == "integration-tests"
Requires-Dist: types-six; extra == "integration-tests"
Requires-Dist: types-freezegun; extra == "integration-tests"
Requires-Dist: packaging; extra == "integration-tests"
Requires-Dist: dagster-snowflake>=0.11.0; extra == "integration-tests"
Requires-Dist: types-pytz; extra == "integration-tests"
Requires-Dist: types-python-dateutil; extra == "integration-tests"
Requires-Dist: requests-mock; extra == "integration-tests"
Requires-Dist: types-PyYAML; extra == "integration-tests"
Requires-Dist: jsonpickle; extra == "integration-tests"
Requires-Dist: twine; extra == "integration-tests"
Requires-Dist: dagster-aws>=0.11.0; extra == "integration-tests"
Requires-Dist: acryl-datahub[datahub-rest,sql-parser]==15.0.4; extra == "integration-tests"
Requires-Dist: mypy>=1.4.0; extra == "integration-tests"
Requires-Dist: pytest-asyncio>=0.16.0; extra == "integration-tests"
Dynamic: classifier
Dynamic: description
Dynamic: description-content-type
Dynamic: home-page
Dynamic: license
Dynamic: project-url
Dynamic: provides-extra
Dynamic: requires-dist
Dynamic: requires-python
Dynamic: summary
